orgasm/__init__.py
orgasm/command_class_inspector.py
orgasm/web.py
orgasm_package-1.3.dist-info/METADATA
orgasm_package-1.3.dist-info/WHEEL
orgasm_package-1.3.dist-info/top_level.txt
orgasm_package-1.3.dist-info/RECORD
