Metadata-Version: 2.4
Name: orgasm-package
Version: 1.3
Summary: Optimized Runtime for Generating Apps, Servers and Modules. ORGASM enables you to convert any class to a command line tool.
Home-page: https://github.com/fantastic001/ORGASM
Author: Stefan Nožinić
Author-email: stefan@lugons.org
License: MIT
Keywords: command line tool
Requires-Dist: argparse
Requires-Dist: argcomplete
Dynamic: author
Dynamic: author-email
Dynamic: home-page
Dynamic: keywords
Dynamic: license
Dynamic: requires-dist
Dynamic: summary
